PyMimircache/__init__.py
PyMimircache/const.py
PyMimircache/version.py
PyMimircache/CMimircache/CacheReader.cpython-36m-darwin.so
PyMimircache/CMimircache/GeneralProfiler.cpython-36m-darwin.so
PyMimircache/CMimircache/Heatmap.cpython-36m-darwin.so
PyMimircache/CMimircache/LRUProfiler.cpython-36m-darwin.so
PyMimircache/cache/__init__.py
PyMimircache/cache/abstractCache.py
PyMimircache/cache/arc.py
PyMimircache/cache/cacheLine.py
PyMimircache/cache/clock.py
PyMimircache/cache/fifo.py
PyMimircache/cache/lru.py
PyMimircache/cache/lruOld.py
PyMimircache/cache/mru.py
PyMimircache/cache/optimal.py
PyMimircache/cache/random.py
PyMimircache/cache/randomv0.py
PyMimircache/cache/s4lru.py
PyMimircache/cache/secondChance.py
PyMimircache/cache/slru.py
PyMimircache/cacheReader/__init__.py
PyMimircache/cacheReader/abstractReader.py
PyMimircache/cacheReader/binaryReader.py
PyMimircache/cacheReader/binaryWriter.py
PyMimircache/cacheReader/csvReader.py
PyMimircache/cacheReader/multiReader.py
PyMimircache/cacheReader/plainReader.py
PyMimircache/cacheReader/requestItem.py
PyMimircache/cacheReader/tracePreprocesser.py
PyMimircache/cacheReader/traceStat.py
PyMimircache/cacheReader/vscsiReader.py
PyMimircache/cacheReader/vscsiReaderOld.py
PyMimircache/profiler/__init__.py
PyMimircache/profiler/cGeneralProfiler.py
PyMimircache/profiler/cHeatmap.py
PyMimircache/profiler/cLRUProfiler.py
PyMimircache/profiler/profilerUtils.py
PyMimircache/profiler/pyGeneralProfiler.py
PyMimircache/profiler/pyHeatmap.py
PyMimircache/profiler/pyHeatmapAux.py
PyMimircache/profiler/pyLRUProfiler.py
PyMimircache/profiler/pyTimeProfiler.py
PyMimircache/profiler/twoDPlots.py
PyMimircache/profiler/utils/__init__.py
PyMimircache/profiler/utils/dist.py
PyMimircache/profiler/utils/splay.py
PyMimircache/top/__init__.py
PyMimircache/top/cachecow.py
PyMimircache/utils/__init__.py
PyMimircache/utils/linkedList.py
PyMimircache/utils/printing.py
PyMimircache-0.0.2.103.dist-info/METADATA
PyMimircache-0.0.2.103.dist-info/RECORD
PyMimircache-0.0.2.103.dist-info/WHEEL
PyMimircache-0.0.2.103.dist-info/top_level.txt
