Metadata-Version: 2.1
Name: PyMimircache
Version: 0.0.2.103
Summary: PyMimircache is a Python3 platform for analyzing cache traces, developed by Juncheng Yang in Ymir group @ Emory University
Home-page: http://mimircache.info
Author: Juncheng Yang
Author-email: peter.waynechina@gmail.com
License: GPLv3
Keywords: PyMimircache cache LRU simulator Emory Ymir
Platform: UNKNOWN
Requires-Dist: heapdict
Requires-Dist: mmh3
Requires-Dist: matplotlib
Requires-Dist: numpy
